odoo/addons/stock_landed_costs_currency/README.rst
odoo/addons/stock_landed_costs_currency/__init__.py
odoo/addons/stock_landed_costs_currency/__manifest__.py
odoo/addons/stock_landed_costs_currency/i18n/stock_landed_costs_currency.pot
odoo/addons/stock_landed_costs_currency/models/__init__.py
odoo/addons/stock_landed_costs_currency/models/stock_landed_cost.py
odoo/addons/stock_landed_costs_currency/models/stock_landed_cost_lines.py
odoo/addons/stock_landed_costs_currency/readme/CONFIGURE.rst
odoo/addons/stock_landed_costs_currency/readme/CONTRIBUTORS.rst
odoo/addons/stock_landed_costs_currency/readme/DESCRIPTION.rst
odoo/addons/stock_landed_costs_currency/readme/USAGE.rst
odoo/addons/stock_landed_costs_currency/static/description/icon.png
odoo/addons/stock_landed_costs_currency/static/description/index.html
odoo/addons/stock_landed_costs_currency/tests/__init__.py
odoo/addons/stock_landed_costs_currency/tests/test_stock_landed_costs_currency.py
odoo/addons/stock_landed_costs_currency/views/stock_landed_cost_views.xml
odoo13_addon_stock_landed_costs_currency-13.0.1.0.1.dev4.dist-info/METADATA
odoo13_addon_stock_landed_costs_currency-13.0.1.0.1.dev4.dist-info/WHEEL
odoo13_addon_stock_landed_costs_currency-13.0.1.0.1.dev4.dist-info/top_level.txt
odoo13_addon_stock_landed_costs_currency-13.0.1.0.1.dev4.dist-info/RECORD
